{
  "generated": "2026-04-29T11:13:10.341Z",
  "pillars": {
    "growth": {
      "score": 0.625,
      "label": "Expanding",
      "color": "green",
      "signals": [
        {
          "ticker": "XLI",
          "name": "Industrials ETF",
          "price": 170.98,
          "change1d": -0.8869019509332369,
          "change1w": -0.268319357977381,
          "change1m": 7.399496862507285,
          "change3m": 3.58657352266336,
          "change6m": 10.373760044884932,
          "change1y": 31.240403231190335,
          "trend": "up",
          "direction": "↑"
        },
        {
          "ticker": "XLY",
          "name": "Consumer Disc ETF",
          "price": 117.01,
          "change1d": -0.7043417885984272,
          "change1w": -1.6474733666990815,
          "change1m": 10.72104636481515,
          "change3m": -4.629554317507175,
          "change6m": -1.531599483951691,
          "change1y": 17.556636189458857,
          "trend": "up",
          "direction": "↑"
        },
        {
          "ticker": "IWM",
          "name": "Russell 2000",
          "price": 273.91,
          "change1d": -1.1654811567123824,
          "change1w": -0.21857348809535457,
          "change1m": 12.673795468962018,
          "change3m": 3.467681144868515,
          "change6m": 9.8143814718177,
          "change1y": 39.685863010637185,
          "trend": "up",
          "direction": "↑"
        },
        {
          "ticker": "^GSPC",
          "name": "S&P 500",
          "price": 7138.8,
          "change1d": -0.489414496213218,
          "change1w": 1.0587476736859072,
          "change1m": 12.089304901595863,
          "change3m": 2.2955851430009977,
          "change6m": 5.1108025583597145,
          "change1y": 28.376514016672843,
          "trend": "up",
          "direction": "→"
        }
      ]
    },
    "inflation": {
      "score": 0.286,
      "label": "Neutral",
      "color": "yellow",
      "signals": [
        {
          "ticker": "CL=F",
          "name": "WTI Crude",
          "price": 103.15,
          "change1d": 3.222255263675254,
          "change1w": 10.961706692947152,
          "change1m": 0.2624458394918621,
          "change3m": 63.186209492000124,
          "change6m": 68.24335216996911,
          "change1y": 70.72162305839986,
          "trend": "flat",
          "direction": "→"
        },
        {
          "ticker": "HG=F",
          "name": "Copper",
          "price": 5.983,
          "change1d": 1.1581665525331848,
          "change1w": -2.238563504659681,
          "change1m": 9.258582633722524,
          "change3m": 1.535848605879457,
          "change6m": 16.38945086504131,
          "change1y": 24.051417342359,
          "trend": "up",
          "direction": "↑"
        },
        {
          "ticker": "GC=F",
          "name": "Gold",
          "price": 4582.6,
          "change1d": -0.1938364368942532,
          "change1w": -3.1674569961701002,
          "change1m": 1.2505545217907645,
          "change3m": -13.561943314394046,
          "change6m": 14.510612696044884,
          "change1y": 38.08002983712066,
          "trend": "down",
          "direction": "↓"
        },
        {
          "ticker": "TIP",
          "name": "TIPS ETF",
          "price": 111.73,
          "change1d": -0.03578477611852325,
          "change1w": 0.4585525360842507,
          "change1m": 1.8783671217126021,
          "change3m": 1.2138816692581773,
          "change6m": -0.21434121742704412,
          "change1y": 1.2138816692581773,
          "trend": "up",
          "direction": "↑"
        },
        {
          "ticker": "DX-Y.NYB",
          "name": "US Dollar (DXY)",
          "price": 98.684,
          "change1d": 0.06489277188768307,
          "change1w": 0.09534615428665352,
          "change1m": -1.8167386225356568,
          "change3m": 2.3162272994853463,
          "change6m": -0.09718634599420481,
          "change1y": -0.5602577265495479,
          "trend": "flat",
          "direction": "→"
        }
      ]
    },
    "policy": {
      "score": 0.222,
      "label": "Neutral",
      "color": "yellow",
      "signals": [
        {
          "ticker": "^TNX",
          "name": "10Y Treasury Yield",
          "price": 4.354,
          "change1d": 0.4151299463745166,
          "change1w": 1.4445544572055296,
          "change1m": -1.9369361387252446,
          "change3m": 3.1020611040332655,
          "change6m": 8.931701636415184,
          "change1y": 3.273244991032725,
          "trend": "flat",
          "direction": "→"
        },
        {
          "ticker": "^FVX",
          "name": "5Y Treasury Yield",
          "price": 3.983,
          "change1d": 0.9120844452385714,
          "change1w": 1.9191414490822591,
          "change1m": -2.1375952810228545,
          "change3m": 4.431047550880395,
          "change6m": 10.577458138906689,
          "change1y": 4.376311739540947,
          "trend": "flat",
          "direction": "→"
        },
        {
          "ticker": "TLT",
          "name": "Long Bond ETF",
          "price": 86.37,
          "change1d": 0.10431296010255113,
          "change1w": -0.23102339025899843,
          "change1m": 0.852409343923736,
          "change3m": -1.6287018855031254,
          "change6m": -5.575596814321209,
          "change1y": -4.246113449269684,
          "trend": "flat",
          "direction": "→"
        },
        {
          "ticker": "HYG",
          "name": "High Yield ETF",
          "price": 80.4,
          "change1d": -0.13663163993503458,
          "change1w": 0.03732584082579341,
          "change1m": 2.134146696041903,
          "change3m": -0.9486222254973488,
          "change6m": -0.8386782064863402,
          "change1y": 1.746399571548942,
          "trend": "up",
          "direction": "↑"
        },
        {
          "ticker": "LQD",
          "name": "IG Credit ETF",
          "price": 109.34,
          "change1d": 0.0457490017877345,
          "change1w": -0.24633178629454208,
          "change1m": 1.5982099492775008,
          "change3m": -1.3265962034931211,
          "change6m": -2.9985848529175665,
          "change1y": 0.783480957561114,
          "trend": "flat",
          "direction": "→"
        },
        {
          "ticker": "DX-Y.NYB",
          "name": "US Dollar (DXY)",
          "price": 98.684,
          "change1d": 0.06489277188768307,
          "change1w": 0.09534615428665352,
          "change1m": -1.8167386225356568,
          "change3m": 2.3162272994853463,
          "change6m": -0.09718634599420481,
          "change1y": -0.5602577265495479,
          "trend": "flat",
          "direction": "→"
        }
      ]
    },
    "sentiment": {
      "score": 0.75,
      "label": "Risk-On",
      "color": "green",
      "signals": [
        {
          "ticker": "SPHB",
          "name": "S&P High Beta",
          "price": 131.52,
          "change1d": -2.033519553072618,
          "change1w": -0.6121042449828357,
          "change1m": 15.886868224576197,
          "change3m": 7.240708518433038,
          "change6m": 14.774420521533948,
          "change1y": 66.12354087946674,
          "trend": "up",
          "direction": "↑"
        },
        {
          "ticker": "SPLV",
          "name": "S&P Low Vol",
          "price": 74.1,
          "change1d": 0.6793499133763011,
          "change1w": 0.8300457587198977,
          "change1m": 2.6742418652384816,
          "change3m": 1.2156800994103556,
          "change6m": 2.348062033720448,
          "change1y": 2.319801639951143,
          "trend": "flat",
          "direction": "→"
        },
        {
          "ticker": "^VIX",
          "name": "VIX",
          "price": 17.95,
          "change1d": 0.6730234257286636,
          "change1w": -5.12684624441342,
          "change1m": -41.35903167257959,
          "change3m": 9.785934826540354,
          "change6m": 13.679549121626088,
          "change1y": -25.73437854249367,
          "trend": "down",
          "direction": "→"
        }
      ]
    }
  },
  "regime": {
    "regime": "Goldilocks",
    "color": "#3b82f6",
    "desc": "Strong growth, contained inflation. Best environment for equities. Favors Growth, Quality, broad exposure.",
    "favored_sectors": [
      "XLK",
      "XLC",
      "XLY"
    ],
    "avoid_sectors": [
      "XLE",
      "XLU"
    ],
    "favored_factors": [
      "QUAL",
      "MTUM",
      "IWF"
    ],
    "avoid_factors": []
  },
  "sectors": {
    "XLK": {
      "name": "State Street Technology Select Sector SPDR ETF",
      "price": 157.85,
      "change1d": -1.6939697329194165,
      "change_1w": 2.0427976031006443,
      "change_1m": 21.497851237844618,
      "change_3m": 6.619387267646164,
      "change_6m": 7.534582276207276,
      "change_1y": 50.980393587718474,
      "sectorName": "Technology"
    },
    "XLF": {
      "name": "State Street Financial Select Sector SPDR ETF",
      "price": 51.85,
      "change1d": 0.07720252007097186,
      "change_1w": -0.8604221214224722,
      "change_1m": 8.450108732034082,
      "change_3m": -2.1698141997715212,
      "change_6m": -2.3724385647717057,
      "change_1y": 6.533799927703372,
      "sectorName": "Financials"
    },
    "XLV": {
      "name": "State Street Health Care Select Sector SPDR ETF",
      "price": 143.84,
      "change1d": 0.2648775047743566,
      "change_1w": -1.4254398692127679,
      "change_1m": 0.40485959325302884,
      "change_3m": -7.46863997315945,
      "change_6m": -1.499693528530477,
      "change_1y": 3.2739787468116823,
      "sectorName": "Health Care"
    },
    "XLE": {
      "name": "State Street Energy Select Sector SPDR ETF",
      "price": 57.71,
      "change1d": 1.6558033021959893,
      "change_1w": 3.2933599208247175,
      "change_1m": -7.752561033173171,
      "change_3m": 16.18683553838767,
      "change_6m": 31.054841113765125,
      "change_1y": 39.51407407899249,
      "sectorName": "Energy"
    },
    "XLI": {
      "name": "State Street Industrial Select Sector SPDR ETF",
      "price": 170.98,
      "change1d": -0.8869019509332369,
      "change_1w": -0.268319357977381,
      "change_1m": 7.399496862507285,
      "change_3m": 3.58657352266336,
      "change_6m": 10.373760044884932,
      "change_1y": 31.240403231190335,
      "sectorName": "Industrials"
    },
    "XLC": {
      "name": "State Street Communication Services Select Sector SPDR ETF",
      "price": 115.75,
      "change1d": -0.05180689047454163,
      "change_1w": -1.2034855053229938,
      "change_1m": 8.137144067614797,
      "change_3m": -0.9837480845749372,
      "change_6m": 0.1730825988404377,
      "change_1y": 21.31851541471887,
      "sectorName": "Communication Svcs"
    },
    "XLY": {
      "name": "State Street Consumer Discretionary Select Sector SPDR ETF",
      "price": 117.01,
      "change1d": -0.7043417885984272,
      "change_1w": -1.6474733666990815,
      "change_1m": 10.72104636481515,
      "change_3m": -4.629554317507175,
      "change_6m": -1.531599483951691,
      "change_1y": 17.556636189458857,
      "sectorName": "Consumer Disc"
    },
    "XLP": {
      "name": "State Street Consumer Staples Select Sector SPDR ETF",
      "price": 83.08,
      "change1d": 0.898717142362616,
      "change_1w": 1.5151582950278792,
      "change_1m": 1.5896344719522257,
      "change_3m": -0.09620229380910808,
      "change_6m": 5.044892752451072,
      "change_1y": 2.264899083787076,
      "sectorName": "Consumer Staples"
    },
    "XLRE": {
      "name": "State Street Real Estate Select Sector SPDR ETF",
      "price": 43.91,
      "change1d": 0.965735353698902,
      "change_1w": 0.29694168967567575,
      "change_1m": 9.747567331888495,
      "change_3m": 6.4484844785748106,
      "change_6m": 2.9542749741020975,
      "change_1y": 6.810992934783617,
      "sectorName": "Real Estate"
    },
    "XLU": {
      "name": "State Street Utilities Select Sector SPDR ETF",
      "price": 46.25,
      "change1d": 0.12990122337072407,
      "change_1w": 2.8921005895340834,
      "change_1m": 1.4476855564885205,
      "change_3m": 6.493206711969893,
      "change_6m": 1.2145755747507863,
      "change_1y": 16.64564494357808,
      "sectorName": "Utilities"
    },
    "XLB": {
      "name": "State Street Materials Select Sector SPDR ETF",
      "price": 51.4,
      "change1d": -0.7338717424783153,
      "change_1w": -0.7146975634791188,
      "change_1m": 5.090986886597887,
      "change_3m": 2.8411404494763643,
      "change_6m": 15.492641933006185,
      "change_1y": 23.172782386099108,
      "sectorName": "Materials"
    }
  },
  "factors": {
    "MTUM": {
      "name": "iShares MSCI USA Momentum Factor ETF",
      "price": 276.21,
      "change1d": -1.617097061442572,
      "change_1w": 1.7010917852215992,
      "change_1m": 17.157277693722257,
      "change_3m": 6.1447967717182665,
      "change_6m": 8.105671802378914,
      "change_1y": 31.962158844207405,
      "factorName": "Momentum"
    },
    "VLUE": {
      "name": "iShares MSCI USA Value Factor ETF",
      "price": 162.11,
      "change1d": -0.8683414602193681,
      "change_1w": 2.4521298031844707,
      "change_1m": 14.906435005919974,
      "change_3m": 10.950653571393138,
      "change_6m": 24.863281463480394,
      "change_1y": 58.32600993915113,
      "factorName": "Value"
    },
    "QUAL": {
      "name": "iShares MSCI USA Quality Factor ETF",
      "price": 205.91,
      "change1d": -0.6177916049632948,
      "change_1w": 0.21901924147645602,
      "change_1m": 9.935931824415903,
      "change_3m": 0.8670541186210521,
      "change_6m": 4.5971771937919685,
      "change_1y": 21.919595243204174,
      "factorName": "Quality"
    },
    "SIZE": {
      "name": "iShares MSCI USA Size Factor ETF",
      "price": 168.24,
      "change1d": -0.6495785766380618,
      "change_1w": -0.725789649306264,
      "change_1m": 7.82542255296569,
      "change_3m": 0.8149571971229209,
      "change_6m": 3.5577979443746437,
      "change_1y": 18.021748082375407,
      "factorName": "Size (Small)"
    },
    "USMV": {
      "name": "iShares MSCI USA Min Vol Factor ETF",
      "price": 93.78,
      "change1d": 0.2244312342211095,
      "change_1w": -0.3294692004030954,
      "change_1m": 2.9192229505443272,
      "change_3m": -1.6259341466338708,
      "change_6m": -0.7619060536541006,
      "change_1y": 2.090135158053712,
      "factorName": "Low Volatility"
    },
    "IWM": {
      "name": "iShares Russell 2000 ETF",
      "price": 273.91,
      "change1d": -1.1654811567123824,
      "change_1w": -0.21857348809535457,
      "change_1m": 12.673795468962018,
      "change_3m": 3.467681144868515,
      "change_6m": 9.8143814718177,
      "change_1y": 39.685863010637185,
      "factorName": "Russell 2000"
    },
    "IWF": {
      "name": "iShares Russell 1000 Growth ETF",
      "price": 476.29,
      "change1d": -0.760512235454231,
      "change_1w": 1.0673510747917014,
      "change_1m": 15.377537211248827,
      "change_3m": 0.3878166910211235,
      "change_6m": -0.1886028399337399,
      "change_1y": 29.87838322411987,
      "factorName": "Russell Growth"
    },
    "IWD": {
      "name": "iShares Russell 1000 Value ETF",
      "price": 227.08,
      "change1d": -0.2591462088507088,
      "change_1w": 0.5357093638043438,
      "change_1m": 8.107592731193897,
      "change_3m": 3.6327158138216,
      "change_6m": 10.07270890543005,
      "change_1y": 24.72125704190531,
      "factorName": "Russell Value"
    }
  },
  "indices": {
    "^GSPC": {
      "name": "S&P 500",
      "price": 7138.8,
      "change1d": -0.489414496213218,
      "change_1w": 1.0587476736859072,
      "change_1m": 12.089304901595863,
      "change_3m": 2.2955851430009977,
      "change_6m": 5.1108025583597145,
      "change_1y": 28.376514016672843
    },
    "^IXIC": {
      "name": "NASDAQ Composite",
      "price": 24663.799,
      "change1d": -0.897254452627671,
      "change_1w": 1.6646351772387307,
      "change_1m": 17.736192795527693,
      "change_3m": 3.555013774816298,
      "change_6m": 6.287178918285015,
      "change_1y": 41.24820082244282
    },
    "^RUT": {
      "name": " Russell 2000 Index",
      "price": 2756.051,
      "change1d": -1.1526812047116306,
      "change_1w": -0.3226046564524419,
      "change_1m": 12.505617167918862,
      "change_3m": 3.3505868411249384,
      "change_6m": 9.651202558713681,
      "change_1y": 39.43952105690018
    },
    "^VIX": {
      "name": "CBOE Volatility Index",
      "price": 17.95,
      "change1d": 0.6730234257286636,
      "change_1w": -5.12684624441342,
      "change_1m": -41.35903167257959,
      "change_3m": 9.785934826540354,
      "change_6m": 13.679549121626088,
      "change_1y": -25.73437854249367
    }
  },
  "commodities": {
    "WTI": {
      "name": "Crude Oil Jun 26",
      "price": 103.15,
      "change1d": 3.222255263675254,
      "change_1w": 10.961706692947152,
      "change_1m": 0.2624458394918621,
      "change_3m": 63.186209492000124,
      "change_6m": 68.24335216996911,
      "change_1y": 70.72162305839986,
      "ticker": "CL=F",
      "commodityName": "WTI Crude"
    },
    "BRENT": {
      "name": "Brent Crude Oil Last Day Financ",
      "price": 107.26,
      "change1d": -3.595184306515406,
      "change_1w": 5.249728468129031,
      "change_1m": -4.894481914181149,
      "change_3m": 56.81286512201174,
      "change_6m": 63.45625974820208,
      "change_1y": 66.94163756611746,
      "ticker": "BZ=F",
      "commodityName": "Brent Crude"
    },
    "NATGAS": {
      "name": "Natural Gas Jun 26",
      "price": 2.662,
      "change1d": 4.025009149161517,
      "change_1w": -2.2042595644437477,
      "change_1m": -7.793562054400066,
      "change_3m": -64.316354862467,
      "change_6m": -22.661243209538075,
      "change_1y": -21.38216168483781,
      "ticker": "NG=F",
      "commodityName": "Natural Gas"
    },
    "COPPER": {
      "name": "Copper May 26",
      "price": 5.983,
      "change1d": 1.1581665525331848,
      "change_1w": -2.238563504659681,
      "change_1m": 9.258582633722524,
      "change_3m": 1.535848605879457,
      "change_6m": 16.38945086504131,
      "change_1y": 24.051417342359,
      "ticker": "HG=F",
      "commodityName": "Copper"
    },
    "GOLD": {
      "name": "Gold Jun 26",
      "price": 4582.6,
      "change1d": -0.1938364368942532,
      "change_1w": -3.1674569961701002,
      "change_1m": 1.2505545217907645,
      "change_3m": -13.561943314394046,
      "change_6m": 14.510612696044884,
      "change_1y": 38.08002983712066,
      "ticker": "GC=F",
      "commodityName": "Gold"
    },
    "SILVER": {
      "name": "Silver May 26",
      "price": 73.295,
      "change1d": 0.12293991762067766,
      "change_1w": -5.902969080739865,
      "change_1m": 4.2247323489963176,
      "change_3m": -35.20082208680408,
      "change_6m": 57.413766025075155,
      "change_1y": 120.27045772467275,
      "ticker": "SI=F",
      "commodityName": "Silver"
    }
  },
  "rates": {
    "^TNX": {
      "name": "CBOE Interest Rate 10 Year T No",
      "price": 4.354,
      "change1d": 0.4151299463745166,
      "change_1w": 1.4445544572055296,
      "change_1m": -1.9369361387252446,
      "change_3m": 3.1020611040332655,
      "change_6m": 8.931701636415184,
      "change_1y": 3.273244991032725,
      "rateName": "10Y Treasury Yield"
    },
    "^FVX": {
      "name": "Treasury Yield 5 Years",
      "price": 3.983,
      "change1d": 0.9120844452385714,
      "change_1w": 1.9191414490822591,
      "change_1m": -2.1375952810228545,
      "change_3m": 4.431047550880395,
      "change_6m": 10.577458138906689,
      "change_1y": 4.376311739540947,
      "rateName": "5Y Treasury Yield"
    },
    "^TYX": {
      "name": "Treasury Yield 30 Years",
      "price": 4.944,
      "change1d": 0.040471221641961055,
      "change_1w": 0.939158963575208,
      "change_1m": -0.7627480484084482,
      "change_3m": 2.317880663995773,
      "change_6m": 7.829874071311542,
      "change_1y": 5.325948282771559,
      "rateName": "30Y Treasury Yield"
    },
    "^IRX": {
      "name": "13 WEEK TREASURY BILL",
      "price": 3.5900002,
      "change1d": 0.000007961857807380077,
      "change_1w": -0.22234950837930634,
      "change_1m": -0.47131127900954833,
      "change_3m": 0.5602235658404272,
      "change_6m": -4.59739826597528,
      "change_1y": -14.381110151548476,
      "rateName": "13-Week T-Bill"
    },
    "DX-Y.NYB": {
      "name": "US Dollar Index",
      "price": 98.684,
      "change1d": 0.06489277188768307,
      "change_1w": 0.09534615428665352,
      "change_1m": -1.8167386225356568,
      "change_3m": 2.3162272994853463,
      "change_6m": -0.09718634599420481,
      "change_1y": -0.5602577265495479,
      "rateName": "US Dollar Index (DXY)"
    },
    "TLT": {
      "name": "iShares 20+ Year Treasury Bond ETF",
      "price": 86.37,
      "change1d": 0.10431296010255113,
      "change_1w": -0.23102339025899843,
      "change_1m": 0.852409343923736,
      "change_3m": -1.6287018855031254,
      "change_6m": -5.575596814321209,
      "change_1y": -4.246113449269684,
      "rateName": "20+ Year Treasury Bond ETF"
    },
    "HYG": {
      "name": "iShares iBoxx $ High Yield Corporate Bond ETF",
      "price": 80.4,
      "change1d": -0.13663163993503458,
      "change_1w": 0.03732584082579341,
      "change_1m": 2.134146696041903,
      "change_3m": -0.9486222254973488,
      "change_6m": -0.8386782064863402,
      "change_1y": 1.746399571548942,
      "rateName": "High Yield Corporate Bond ETF"
    },
    "LQD": {
      "name": "iShares iBoxx $ Investment Grade Corporate Bond ETF",
      "price": 109.34,
      "change1d": 0.0457490017877345,
      "change_1w": -0.24633178629454208,
      "change_1m": 1.5982099492775008,
      "change_3m": -1.3265962034931211,
      "change_6m": -2.9985848529175665,
      "change_1y": 0.783480957561114,
      "rateName": "Investment Grade Bond ETF"
    }
  },
  "ideas": {
    "own": [
      {
        "ticker": "AMZN",
        "name": "Amazon",
        "subsector": "Hyperscalers",
        "sectorEtf": "XLK",
        "sectorName": "Technology",
        "reason": "In favored sector (Technology) for Goldilocks regime"
      },
      {
        "ticker": "GOOG",
        "name": "Google",
        "subsector": "Hyperscalers",
        "sectorEtf": "XLK",
        "sectorName": "Technology",
        "reason": "In favored sector (Technology) for Goldilocks regime"
      },
      {
        "ticker": "META",
        "name": "Meta",
        "subsector": "Hyperscalers",
        "sectorEtf": "XLK",
        "sectorName": "Technology",
        "reason": "In favored sector (Technology) for Goldilocks regime"
      },
      {
        "ticker": "MSFT",
        "name": "Microsoft",
        "subsector": "Hyperscalers",
        "sectorEtf": "XLK",
        "sectorName": "Technology",
        "reason": "In favored sector (Technology) for Goldilocks regime"
      },
      {
        "ticker": "NVDA",
        "name": "NVIDIA",
        "subsector": "Semiconductors",
        "sectorEtf": "XLK",
        "sectorName": "Technology",
        "reason": "In favored sector (Technology) for Goldilocks regime"
      }
    ],
    "avoid": [
      {
        "ticker": "SOC",
        "name": "Sable Offshore",
        "subsector": "Energy",
        "sectorEtf": "XLE",
        "sectorName": "Energy",
        "reason": "In unfavored sector (Energy) for Goldilocks regime"
      },
      {
        "ticker": "GEV",
        "name": "GE Vernova",
        "subsector": "Power & Utilities",
        "sectorEtf": "XLU",
        "sectorName": "Utilities",
        "reason": "In unfavored sector (Utilities) for Goldilocks regime"
      },
      {
        "ticker": "VLO",
        "name": "VLO",
        "subsector": "Energy",
        "sectorEtf": "XLE",
        "sectorName": "Energy",
        "reason": "In unfavored sector (Energy) for Goldilocks regime"
      },
      {
        "ticker": "FANG",
        "name": "FANG",
        "subsector": "Energy",
        "sectorEtf": "XLE",
        "sectorName": "Energy",
        "reason": "In unfavored sector (Energy) for Goldilocks regime"
      },
      {
        "ticker": "BKR",
        "name": "BKR",
        "subsector": "Energy",
        "sectorEtf": "XLE",
        "sectorName": "Energy",
        "reason": "In unfavored sector (Energy) for Goldilocks regime"
      }
    ]
  }
}